martrem/__init__.py
martrem/cleaning.py
martrem/autoenc/__init__.py
martrem/autoenc/autoencoder.py
martrem/aux/__init__.py
martrem/aux/filtering.py
martrem/aux/scaling.py
martrem/aux/templating.py
magnes_artifact_removal-0.1.0.dist-info/METADATA
magnes_artifact_removal-0.1.0.dist-info/WHEEL
magnes_artifact_removal-0.1.0.dist-info/licenses/LICENSE
magnes_artifact_removal-0.1.0.dist-info/RECORD
