Metadata-Version: 2.4
Name: magnes-artifact-removal
Version: 0.1.0
Summary: Magnes utility for the removal of artifacts from timeseries.
Author-email: Alessandro Schaer <aschaer@magnes.ch>, Henrik Maurenbrecher <henrikm@magnes.ch>
License-File: LICENSE
Requires-Python: >=3.12
Requires-Dist: magnes-signal-generation-utility
Requires-Dist: matplotlib>=3.10.6
Requires-Dist: numpy>=2.3.3
Requires-Dist: onnxruntime>=1.23.0
Requires-Dist: scikit-learn>=1.7.2
Requires-Dist: scipy>=1.16.2
Requires-Dist: skl2onnx>=1.19.1
Requires-Dist: torch>=2.8.0
